RotaryMenu/RotaryMenuClasses.py
RotaryMenu/__init__.py
RotaryMenu/encoder.py
rpi_rotary_menu-0.0.10.dist-info/licenses/LICENSE
rpi_rotary_menu-0.0.10.dist-info/METADATA
rpi_rotary_menu-0.0.10.dist-info/WHEEL
rpi_rotary_menu-0.0.10.dist-info/top_level.txt
rpi_rotary_menu-0.0.10.dist-info/RECORD
