Metadata-Version: 2.4
Name: RPi.rotary-menu
Version: 0.0.10
Summary: A Python library for Raspberry Pi to display and control a rotary menu on a CharLCD.
Author-email: FyrfyX8 <f.norbisrath@web-n-office.de>
Project-URL: Homepage, https://github.com/FyrfyX8/RotaryMenu
Project-URL: Bug Tracker, https://github.com/FyrfyX8/RotaryMenu/issues
Classifier: Programming Language :: Python :: 3
Classifier: License :: OSI Approved :: MIT License
Classifier: Operating System :: Other OS
Classifier: Topic :: Software Development :: Libraries :: Python Modules
Requires-Python: >=3.10
License-File: LICENSE
Dynamic: license-file
